[
  {
    "id": "hospice-1106225323",
    "type": "hospice",
    "name": "Barnsley Hospice",
    "lat": 53.560704,
    "lng": -1.514754,
    "address": "104-106 Church Street, Barnsley, South Yorkshire"
  },
  {
    "id": "hospice-1106749761",
    "type": "hospice",
    "name": "Lindsey Lodge Hospice",
    "lat": 53.564926,
    "lng": -0.689741,
    "address": "Burringham Road, Scunthorpe, Lincolnshire"
  },
  {
    "id": "hospice-1108415043",
    "type": "hospice",
    "name": "St Luke's Hospice Sheffield",
    "lat": 53.343874,
    "lng": -1.521647,
    "address": "Little Common Lane, Whirlowdale, Sheffield, South Yorkshire"
  },
  {
    "id": "hospice-1108982844",
    "type": "hospice",
    "name": "Wakefield Hospice",
    "lat": 53.697493,
    "lng": -1.483983,
    "address": "Aberford Road, Wakefield, West Yorkshire"
  },
  {
    "id": "hospice-1109728988",
    "type": "hospice",
    "name": "St Gemma's Hospice",
    "lat": 53.842326,
    "lng": -1.534185,
    "address": "329 Harrogate Road, Moortown, Leeds, West Yorkshire"
  },
  {
    "id": "hospice-1110304719",
    "type": "hospice",
    "name": "Bluebell Wood Children's Hospice",
    "lat": 53.360514,
    "lng": -1.22952,
    "address": "Cramfit Road, North Anston, Sheffield, South Yorkshire"
  },
  {
    "id": "hospice-1110432954",
    "type": "hospice",
    "name": "Dove House Hospice",
    "lat": 53.76416,
    "lng": -0.319701,
    "address": "Chamberlain Road, Hull, Humberside"
  },
  {
    "id": "hospice-1112322887",
    "type": "hospice",
    "name": "North Yorkshire Hospice Care",
    "lat": 53.976876,
    "lng": -1.518812,
    "address": "Hornbeam Park Avenue, Harrogate"
  },
  {
    "id": "hospice-1115011048",
    "type": "hospice",
    "name": "Kirkwood Hospice",
    "lat": 53.650016,
    "lng": -1.739117,
    "address": "21 Albany Road, Dalton, Huddersfield, West Yorkshire"
  },
  {
    "id": "hospice-1117082540",
    "type": "hospice",
    "name": "St Leonard's Hospice York",
    "lat": 53.932182,
    "lng": -1.111782,
    "address": "185 Tadcaster Road, York, North Yorkshire"
  },
  {
    "id": "hospice-1118324618",
    "type": "hospice",
    "name": "Overgate Hospice",
    "lat": 53.684129,
    "lng": -1.851478,
    "address": "30 Hullen Edge Road, Elland, West Yorkshire"
  },
  {
    "id": "hospice-1119399738",
    "type": "hospice",
    "name": "Marie Curie Hospice Bradford",
    "lat": 53.79429,
    "lng": -1.733535,
    "address": "Maudsley Street, Bradford, West Yorkshire"
  },
  {
    "id": "hospice-1119619768",
    "type": "hospice",
    "name": "Prince of Wales Hospice",
    "lat": 53.688605,
    "lng": -1.329441,
    "address": "Halfpenny Lane, Pontefract, West Yorkshire"
  },
  {
    "id": "hospice-1119796870",
    "type": "hospice",
    "name": "St Andrew's Hospice Grimsby",
    "lat": 53.551095,
    "lng": -0.073824,
    "address": "Peaks Lane, Grimsby, Lincolnshire"
  },
  {
    "id": "hospice-1136414769",
    "type": "hospice",
    "name": "Sue Ryder Manorlands Hospice",
    "lat": 53.81327,
    "lng": -1.95123,
    "address": "Oxenhope, Keighley, West Yorkshire"
  },
  {
    "id": "hospice-1136414799",
    "type": "hospice",
    "name": "Sue Ryder Wheatfields Hospice",
    "lat": 53.821261,
    "lng": -1.573775,
    "address": "Grove Road, Headingley, Leeds, West Yorkshire"
  },
  {
    "id": "hospice-1192647261",
    "type": "hospice",
    "name": "The Rotherham Hospice",
    "lat": 53.424065,
    "lng": -1.340785,
    "address": "Broom Road, Rotherham, South Yorkshire"
  },
  {
    "id": "hospice-124208897048",
    "type": "hospice",
    "name": "Lambert Hospice Thirsk",
    "lat": 54.231693,
    "lng": -1.342399,
    "address": "Chapel Street, Thirsk, North Yorkshire"
  },
  {
    "id": "hospice-1442758792",
    "type": "hospice",
    "name": "Forget Me Not Children's Hospice",
    "lat": 53.675962,
    "lng": -1.773229,
    "address": "Fell Greave Road, Huddersfield, West Yorkshire"
  }
]