{
  "hosp-east_surrey_hospital": {
    "tool": "O",
    "date": "2026-03-28",
    "user": "James Morris",
    "ew": null
  },
  "hosp-spire_gatwick_park_hospita": {
    "tool": "O",
    "date": "2026-03-28",
    "user": "James Morris",
    "ew": null
  },
  "hospice-1-17592565333": {
    "tool": "O",
    "ew": null,
    "date": "2026-04-01",
    "user": "James Morris"
  },
  "hosp-princess_alexandra_hospita": {
    "tool": "MG",
    "ew": null,
    "date": "2026-04-23",
    "user": "James Morris",
    "name": "Princess Alexandra Hospital"
  },
  "hosp-queen_victoria_hospital": {
    "tool": "O",
    "ew": null,
    "date": "2026-04-24",
    "user": "James Morris",
    "name": "Queen Victoria Hospital"
  }
}