[{"id":"uni-10001143","type":"university","name":"Canterbury Christ Church University","postcode":"CT1 1QU","lat":51.2773,"lng":1.0789,"address":""},{"id":"uni-10003614","type":"university","name":"The University of Winchester","postcode":"SO22 4NR","lat":51.06,"lng":-1.316,"address":""},{"id":"uni-10005523","type":"university","name":"Rose Bruford College of Theatre and Performance","postcode":"DA15 9DF","lat":51.4227,"lng":0.0875,"address":""},{"id":"uni-10006022","type":"university","name":"Southampton Solent University","postcode":"SO14 0YN","lat":50.906,"lng":-1.402,"address":""},{"id":"uni-10007843","type":"university","name":"St Mary's University, Twickenham","postcode":"TW1 4SX","lat":51.4452,"lng":-0.3362,"address":""},{"id":"uni-10000886","type":"university","name":"The University of Brighton","postcode":"BN2 4AT","lat":50.823,"lng":-0.141,"address":""},{"id":"uni-10003678","type":"university","name":"Kingston University","postcode":"KT1 2EE","lat":51.412,"lng":-0.301,"address":""},{"id":"uni-10004930","type":"university","name":"Oxford Brookes University","postcode":"OX3 0BP","lat":51.7488,"lng":-1.22,"address":""},{"id":"uni-10007155","type":"university","name":"The University of Portsmouth","postcode":"PO1 2UP","lat":50.798,"lng":-1.093,"address":""},{"id":"uni-10007137","type":"university","name":"The University of Chichester","postcode":"PO19 6PE","lat":50.8378,"lng":-0.778,"address":""},{"id":"uni-10000961","type":"university","name":"Brunel University London","postcode":"UB8 3PH","lat":51.5322,"lng":-0.4754,"address":""},{"id":"uni-10007150","type":"university","name":"The University of Kent","postcode":"CT2 7NZ","lat":51.2981,"lng":1.068,"address":""},{"id":"uni-10005553","type":"university","name":"Royal Holloway and Bedford New College","postcode":"TW20 0EX","lat":51.4256,"lng":-0.5651,"address":""},{"id":"uni-10007774","type":"university","name":"The University of Oxford","postcode":"OX1 2JD","lat":51.7548,"lng":-1.2544,"address":""},{"id":"uni-10007802","type":"university","name":"The University of Reading","postcode":"RG6 6AH","lat":51.4414,"lng":-0.9429,"address":""},{"id":"uni-10007158","type":"university","name":"The University of Southampton","postcode":"SO17 1BJ","lat":50.9345,"lng":-1.3951,"address":""},{"id":"uni-10007160","type":"university","name":"The University of Surrey","postcode":"GU2 7XH","lat":51.2436,"lng":-0.5886,"address":""},{"id":"uni-10007806","type":"university","name":"The University of Sussex","postcode":"BN1 9RH","lat":50.8657,"lng":-0.0878,"address":""},{"id":"uni-10006427","type":"university","name":"University for the Creative Arts","postcode":"GU9 7DS","lat":51.2961,"lng":-0.508,"address":""},{"id":"uni-10067853","type":"university","name":"ACM Guildford Limited","postcode":"GU1 4QU","lat":51.2361,"lng":-0.574,"address":""},{"id":"uni-10005378","type":"university","name":"Rambert School","postcode":"TW1 1QN","lat":51.4838,"lng":-0.3135,"address":""},{"id":"uni-extra-London_School_of_The","type":"university","name":"London School of Theology","postcode":"HA8 6JW","lat":51.5971,"lng":-0.3116,"address":""},{"id":"uni-extra-Regent_College_Londo","type":"university","name":"Regent College London","postcode":"HA2 8TS","lat":51.5085,"lng":-0.0937,"address":""},{"id":"uni-extra-Waverley_Abbey_Colle","type":"university","name":"Waverley Abbey College","postcode":"GU9 8EP","lat":51.187,"lng":-0.796,"address":""},{"id":"uni-extra-BCNO_Limited","type":"university","name":"BCNO Limited","postcode":"HA8 0DA","lat":51.5971,"lng":-0.3116,"address":""}]